cantopy/__init__.py
cantopy/download_manager.py
cantopy/fetch_manager.py
cantopy/py.typed
cantopy/xenocanto_components/__init__.py
cantopy/xenocanto_components/query.py
cantopy/xenocanto_components/query_result.py
cantopy/xenocanto_components/recording.py
cantopy/xenocanto_components/result_page.py
cantopy-0.2.6.dist-info/LICENSE
cantopy-0.2.6.dist-info/METADATA
cantopy-0.2.6.dist-info/WHEEL
cantopy-0.2.6.dist-info/RECORD
